qrev_cache/__init__.py
qrev_cache/base_cache.py
qrev_cache/file_cache.py
qrev_cache/in_memory_cache.py
qrev_cache/models.py
qrev_cache/mongo_cache.py
qrev_cache/py.typed
qrev_cache/utils/time_utils.py
qrev_cache-0.2.3.dist-info/METADATA
qrev_cache-0.2.3.dist-info/WHEEL
qrev_cache-0.2.3.dist-info/RECORD
